{"id":"4470451853","adHeader":"DRAWINGS - DESIGN - BUILDING PERMIT ..low rates","adLink":"http://sfbay.craigslist.org/sby/sks/4470451853.html","adDetails":"BUILDING PERMIT - RESIDENTIAL PROJECTS COMPLETE SET OF PLANS: Architectural plans Structural calculations and plans (by licensed Engineer) Title 24 energy compliance, Please contact by email or call show contact info","postDate":"2014-06-10T21:05:30-0700","subCategory":{"category":"skilled trade services","link":"http://sfbay.craigslist.org/sks/"},"location":{"lattitude":null,"longitude":null,"info":"License info: Available"}}