{"id":"4475884069","adHeader":"$175 Timming belt, water pump, tensioner replacement","adLink":"http://sfbay.craigslist.org/eby/aos/4475884069.html","adDetails":"Timming belt , water pump, tensioner replacement $ 175.00 labor for Honda, Toyota, Mazda and Nissian Fast and reliable call John show contact info","postDate":"2014-06-10T21:50:05-0700","subCategory":{"category":"automotive services","link":"http://sfbay.craigslist.org/aos/"},"location":{"lattitude":"38.158200","longitude":"-122.280400","info":""}}