{"id":"4480621575","adHeader":"flagstone,garden stone construction","adLink":"http://sfbay.craigslist.org/nby/fgs/4480621575.html","adDetails":"IF YOU WANT NICE GARDEN WITH NEW LAWN SPRINKLERS SYSTEM GOOD SOIL. ALSO WE DO STONE WORKS> PATIOS, NATURAL STONES RETAINING WALLS. CONCRETE WORKS> DRIVEWAYS,SIDEWALKS,STAMPAD CONCRETE. WOOD WORKS> DECKS SENDER AND STAIN FENCES DECKS RETAINING WALLS. LOW PRICE FREE ESTIMATES REFERENCES AVAILABLE CALL JULIO show contact info www.julioslandscapeconstruction.com .","postDate":"2014-06-10T21:06:39-0700","subCategory":{"category":"farm & garden services","link":"http://sfbay.craigslist.org/fgs/"},"location":{"lattitude":null,"longitude":null,"info":""}}