{"id":"4481526796","adHeader":"(((((( HAULING SERVICES JUNK REMOVAL )))))))","adLink":"http://sfbay.craigslist.org/sby/lbs/4481526796.html","adDetails":"PROFESSIONAL HAULING SERVICES JUNK REMOVAL CALL ME TODAY show contact info GABINO FREE ESTIMATES DUMPS RUNS:OFFICE AND STORAGE CLEAN OUTS GARAGE CLEAN OUTS, TRASH REMOVAL OLD FURNITURE REMOVAL, JACUZZI REMOVAL CONSTRUCTION REMOVAL, YARD CLEAN UP DEBRIS REMOVAL, DIRT REMOVAL, WOOD REMOVAL PATIO CLEAN UP, FENCE REMOVAL, ETC... All bay area","postDate":"2014-06-10T20:33:45-0700","subCategory":{"category":"labor & moving","link":"http://sfbay.craigslist.org/lbs/"},"location":{"lattitude":"37.282700","longitude":"-121.826500","info":""}}