{"id":"4483755918","adHeader":"\"\"\"\"\"\"\"\"\"\"ROOF,FENCE,GUTTER,LANDSCAPE\"\"\"\"\"\"\"\"\"\"\"","adLink":"http://sfbay.craigslist.org/eby/hss/4483755918.html","adDetails":"ALL TYPES OF ROOFING =FENCE =GUTTERS =SKYLGHTS =CONCRETE =PAINTING =ADDITIONS =CARPENTER =MORE INDEPENDENT HANDYMAN WITH 25 YEARS EXPERIENCE HAVE TOOLS AND SMALL TRUCK AT YOUR SERVICE FOR LOW RATE ANY JOB ANY TIME HONEST RELIABLE FAST QUALITY WORK 100% GRANTED WORK REFERENCES UPON REQUEST JOBS INCLUDES ..GARDENING...SHAMPOO CARPET...PLUMBING.. ....PRESSURE WASHER DRIVE WAY BACK YARDS ....CARPENTRY WALLS CEILING ..ROOF GUTTERS .. WINDOWS DOORS ..TILE WORK FLOOR WORK... BATH ROOM AND KITCHEN SINK ...ANY WATER LEAKS ..HEATING....FIX... REPAIR... REPLACE WITH NEW ONE ..ANY JOB SMALL OR LARGE INSTALL NEW AC IN WINDOWS OR WALLS NEW SKYLIGHT ...PLEASE CALL ME . Daniel NOTA: I CHANGE THE PHONE NUMBER show contact info","postDate":"2014-06-10T19:37:05-0700","subCategory":{"category":"household services","link":"http://sfbay.craigslist.org/hss/"},"location":{"lattitude":null,"longitude":null,"info":""}}