{"id":"4486307931","adHeader":"AIRPORT SHUTTLE / PRIVATE DRIVER","adLink":"http://sfbay.craigslist.org/sby/trv/4486307931.html","adDetails":"AFFORDABLE , RELIABLE AIRPORT SERVICES . OFFERING FLAT RATE TO ALL AIRPORT . SFO - SJC - OAK PERSONAL DRIVER APPOINTMENT, WORKING , ERRANDS , SCHOOL , CONCERT etc Accepting Credit Cards , PayPal and providing receipts . Call , Text or Email show contact info . THANK YOU ,","postDate":"2014-06-10T21:26:37-0700","subCategory":{"category":"travel/vacation services","link":"http://sfbay.craigslist.org/trv/"},"location":{"lattitude":"37.398300","longitude":"-122.000600","info":""}}