{"id":"4507791173","adHeader":"SLOW COMPUTER? VIRUS/SPYWARE? FIX YOUR LAPTOP or PC ->$49 SPECIAL","adLink":"http://sfbay.craigslist.org/eby/cps/4507791173.html","adDetails":"JOIN OUR FACEBOOK PAGE: http://www.facebook.com/pages/Shawn-East-Bay-Enterprise-Computer-Services/498975273479620 EAST BAY COMPUTER SERVICE. CALL TODAY show contact info. Honest, Secure, and Reliable -- independent and locally owned full service for Over 10 Years. +EXPERT VIRUS/MALWARE REMOVAL, INCLUDES SYSTEM TUNE-UP +DATA RECOVERY +CONFIDENTIAL DATA MANAGEMENT +LAPTOP REPAIRS (BROKEN SCREENS, KEYBOARDS, POWER JACKS, ETC...) +WINDOWS REPAIR (BLUE SCREENS, ETC) AND UPGRADES +NETWORK TROUBLESHOOTING +REMOTE SUPPORT +PICK UP & DELIVERY SERVICE +MANAGED OFFSITE DATA BACKUP SOLUTIONS +CUSTOM BUILDS +EMERGENCY AFTER HOURS SUPPORT CALL TODAY show contact info.","postDate":"2014-06-10T19:53:50-0700","subCategory":{"category":"computer services","link":"http://sfbay.craigslist.org/cps/"},"location":{"lattitude":null,"longitude":null,"info":""}}