{"id":"4509911409","adHeader":"[Best-Helpers]=[Best-Move]=[Low-Price][[[$50]]]","adLink":"http://sfbay.craigslist.org/nby/lbs/4509911409.html","adDetails":"help for you-_-local (santa rosa) help for you-local (sonoma county) [Best-Helpers]_[Best-Move]_[Low-Price] [$50] (healdsburg / windsor) hello,good day! Send a E-mail if you need load or unload your truck we can help you. if you need pack or unpack your things we can help you. need delivery!!! we can help!!! junk removal and trash removal!!! garbage removal and dump runs!!! and clean outs for you!!! ===========$50 dollars 2 helpers at your service======= -","postDate":"2014-06-10T19:47:41-0700","subCategory":{"category":"labor & moving","link":"http://sfbay.craigslist.org/lbs/"},"location":{"lattitude":null,"longitude":null,"info":""}}