{"id":"4512375065","adHeader":"PROFESSIONAL MOVING AND LABOR /FAST DELIVERY ,STORAGE,HOUSE,APRT","adLink":"http://sfbay.craigslist.org/sfc/lbs/4512375065.html","adDetails":"PROFESSIONAL MOVING AND LABOR! FAST -DELIVERY ,HOUSHOLD BELONGS,CRAIGLIST FURNITURE STORAGE,HOUSE , APARTMENT,OFFICE MOVERS HERE SUPER FRIENDLY GOOD BEST QUALITY MOVERS ...................................................................................................................... FREE ; PACKING FURNITURE / UNPACKING FREE/ TOOLS,HANDTRUCKS,WORDROB BOXES LOADING TRUCK AND UNLOADING /LABOR MOVERS CREW- 2 M_o_v_e_r_s with 20 ft truck 65$ per hour 2 MIN CREW- 3 MOVERS WITH 24 FT TRUCK 85$ PER HOUR3MIN CREW- 4 MOVERS WITH 26 FT TRUCK 100$ PER HOUR 3 MIN PLEASE CALL show contact info aLEX THANK YOU!","subCategory":{"category":"labor & moving","link":"http://sfbay.craigslist.org/lbs/"},"location":{"lattitude":"37.759300","longitude":"-122.483600","info":""}}