{"id":"4514787527","adHeader":"////////Francielly Lima////House Clean/////////","adLink":"http://sfbay.craigslist.org/sfc/hss/4514787527.html","adDetails":"We clean Houses, Apartments, Offices, Studios ONCE A WEEK , TWICE A WEEK , ONCE A MONTH ,  AVAILABLE 7 DAYS A WEEK REGULAR CLEANING DEEP CLEANING MOVING IN/OUT CLEANING Scrub/Clean Shower/bathtubs  Scrub Toilet Deodorize Bathroom  Dust all surfaces Wipe all surfaces  Sweep/Mop or vacuum ALL floors Kitchen Cleaning  Clean all appliances  SAN RAMON / HAYWARD / CONCORD /DANVILLE / BENICIA/ PLEASANT HILL/ SUISUN BAY/CITY FAIRFIELD .","postDate":"2014-06-10T21:49:06-0700","subCategory":{"category":"household services","link":"http://sfbay.craigslist.org/hss/"},"location":{"lattitude":"37.926500","longitude":"-122.334200","info":""}}