{"id":"4514487971","adHeader":"YOU HAVE TRIED THE REST NOW TRY THE BEST","adLink":"http://sfbay.craigslist.org/eby/bts/4514487971.html","adDetails":"NEWARK EXCELLENT MASSAGE 6170 Thornton Ave.Suite I Newark,Ca.94560 show contact info We Specialize in Relieving: Stress Anxiety Headaches Neck and Shoulder Pain Back Pain Lower Back Pain Hours 10:00am to 9:00pm LAST APPT.8:00PM PLEASE Monday thru Sunday Walk-ins Welcome,CALL US FOR APPOINTMENT show contact info We accept Master,Visa Cards ~~~~~ THANK YOU ~~~~~ WE HOPE TO SEE YOU SOON","postDate":"2014-06-10T17:21:50-0700","subCategory":{"category":"beauty services","link":"http://sfbay.craigslist.org/bts/"},"location":{"lattitude":"37.535815","longitude":"-122.031176","info":"6170 Thornton Avenue "}}