{"id":"4514714771","adHeader":"MAC MAKE UP ARTIST READY FOR HIRE","adLink":"http://sfbay.craigslist.org/eby/bts/4514714771.html","adDetails":"ALL OCCASION MAKE UP ARTIST, 6+ YEARS MAC MAKE UP ARTIST EXPERIENCE. FOR BOOKINGS, QUESTIONS, OR PRICING PLEASE CONTACT ME. ALSO CHECK OUT MY MAKE UP SITE ON FACEBOOK FOR PICTURES. WWW.FACEBOOK.COM/MAKEUPBYMORSAL EMAIL: show contact info CALL OR TEXT show contact info","postDate":"2014-06-10T20:23:24-0700","subCategory":{"category":"beauty services","link":"http://sfbay.craigslist.org/bts/"},"location":{"lattitude":null,"longitude":null,"info":""}}