{"id":"4514848180","adHeader":"GARAGE DOORS","adLink":"http://sfbay.craigslist.org/sfc/hss/4514848180.html","adDetails":"Are you in need of prompt, affordable garage door repairs? Our certified technicians are qualified and honest. All our trucks are fully stocked so we can fix your door quickly and professionally. We repair/replace all types of doors (wood, steel, composite) as well as: Broken Springs Cables Hinge Arms Gears & Sprockets Remotes Sensor Eyes Panel Replacements Circuit boards Weatherstrip Rollers and more CALL CR GARAGE DOORS TODAY show contact info","postDate":"2014-06-10T23:43:21-0700","subCategory":{"category":"household services","link":"http://sfbay.craigslist.org/hss/"},"location":{"lattitude":"37.530800","longitude":"-121.971200","info":""}}