{"id":"4514827912","adHeader":"Best Woodworker","adLink":"http://sfbay.craigslist.org/eby/sks/4514827912.html","adDetails":"azizfinewoodworking.com Aziz Abbatiello- Best Woodworker in the Bay Area. BAHA award recipient. Highly skilled in furniture, craftsman homes, cabinetry, built-ins, hand-carving, high-end fences with arbors, stairs, doors, and windows. I have a full shop in Berkeley and can handle all forms of custom woodwork. No job is too big or too small. Shop rate is $85 On site rate $65 also available for: millwork, trim packages, finish carpentry, mock-ups and design. Please i will only respond if you include a phone number when you reply Thank you","postDate":"2014-06-10T22:56:16-0700","subCategory":{"category":"skilled trade services","link":"http://sfbay.craigslist.org/sks/"},"location":{"lattitude":null,"longitude":null,"info":"License info: Unlicensed"}}