{"id":"4514668430","adHeader":"Tennis Racquet Stringer","adLink":"http://sfbay.craigslist.org/sby/sks/4514668430.html","adDetails":"Hello I string racquets and I will gladly string yours. Each racquet costs $20 and if I have to buy strings then strings are added on to the price of the stringing. I have been stringing racquets for 4 years and have done it for my friends and local tennis players. I use a Gamma drop weight stringer. Feel free to contact me.","postDate":"2014-06-10T19:40:20-0700","subCategory":{"category":"skilled trade services","link":"http://sfbay.craigslist.org/sks/"},"location":{"lattitude":"37.260200","longitude":"-121.770900","info":""}}