{"id":"4514568827","adHeader":"We rent, tables, chairs, jumper,waterslide canopies","adLink":"http://sfbay.craigslist.org/eby/evs/4514568827.html","adDetails":"We rent tables, chairs, jumpers,waterslide, tents, cotton machine, popcorn and scraping. Decorations are made for all types of events. For more information call tell show contact info or send a text message. Se rentan Mesas,Sillas,Carpas,Jumper,jumper de agua,Maquinas de algodon,palomitas y raspados. Se hacen arreglos de salon de mesa para todo tipo de eventos contamos con manteleria y cubre sillas. para mas informacion llamar al show contact info o mandar mensaje de texto. Hayward, Castro Valley, San Lorenso, Union City, Fremont, San Leandro, Newark, Dublin y Pleasanton. And we're so well in the area of SanJoaquin. Stockton,Manteca,French Camp,Ripon,Lodi,Tracy.","postDate":"2014-06-10T18:20:24-0700","subCategory":{"category":"event services","link":"http://sfbay.craigslist.org/evs/"},"location":{"lattitude":null,"longitude":null,"info":""}}