{"id":"4514713481","adHeader":"*****PERFECT HOUSE CLEAN******","adLink":"http://sfbay.craigslist.org/sfc/hss/4514713481.html","adDetails":"***PERFECT HOUSE CLEAN*** (San francisco) we are 10 years in the home cleaning market with great references. we cleaned houses apartments offices.move in -out we have great prices and excelent job. also we do deep clean. thanks. show contact info. Percival.","postDate":"2014-06-10T20:22:07-0700","subCategory":{"category":"household services","link":"http://sfbay.craigslist.org/hss/"},"location":{"lattitude":null,"longitude":null,"info":""}}